LICENSE
MANIFEST.in
README.md
setup.py
python_pip_package_starter_kit.egg-info/PKG-INFO
python_pip_package_starter_kit.egg-info/SOURCES.txt
python_pip_package_starter_kit.egg-info/dependency_links.txt
python_pip_package_starter_kit.egg-info/top_level.txt
src/__init__.py
src/foo_bar.py