Metadata-Version: 1.0
Name: python-pip-package-starter-kit
Version: 0.0.2
Summary: Sample package from Schubert
Home-page: https://github.com/rfschubert/python-pip-package-starter-kit
Author: Raphael Schubert
Author-email: rfswdp@gmail.com
License:                     GNU GENERAL PUBLIC LICENSE
